SingleCycleCPU.sv
`timescale 1ns/1ps


module SingleCycleCPU(
    input logic clk,
    input logic reset
);


    logic [31:0] PC; 
    logic [31:0] instr_mem [0:255]; // 指令存储器，256 条指令，每条 32 位
    logic [31:0] instruction; 


    initial begin
        $readmemh("instr_mem.hex", instr_mem);
    end

  
    always_ff @(posedge clk or posedge reset) begin
        if (reset)
            PC <= 32'd0;
        else
            PC <= PC + 32'd4;
    end


    assign instruction = instr_mem[PC[9:2]];


    logic [31:0] regs [0:31];
    integer i;
    
	 always_ff @(posedge clk or posedge reset) begin
        if (reset) begin
            for (i = 0; i < 32; i = i + 1)
                regs[i] <= 32'd0;
        end else begin
        end
    end


    wire [31:0] rs1_data = (instruction[19:15] == 5'd0) ? 32'd0 : regs[instruction[19:15]];
    wire [31:0] rs2_data = (instruction[24:20] == 5'd0) ? 32'd0 : regs[instruction[24:20]];


    logic [6:0] opcode;
    logic [4:0] rd;
    logic [2:0] funct3;
    logic [4:0] rs1, rs2;
    logic [6:0] funct7;
    logic [31:0] imm;

    always_comb begin
        
		  opcode = instruction[6:0];
        rd     = instruction[11:7];
        funct3 = instruction[14:12];
        rs1    = instruction[19:15];
        rs2    = instruction[24:20];
        funct7 = instruction[31:25];

        imm = {{20{instruction[31]}}, instruction[31:20]};
    end

    
	 logic [31:0] alu_result;

    always_comb begin
      
        alu_result = 32'd0;
        
		  if (opcode == 7'b0010011) begin  // ADDI
            alu_result = rs1_data + imm;
        end else if (opcode == 7'b0110011) begin // R-type
            if (funct3 == 3'b000) begin
                if (funct7 == 7'b0100000)
                    alu_result = rs1_data - rs2_data; // SUB
                else
                    alu_result = rs1_data + rs2_data; // ADD
            end
            
        end else if (opcode == 7'b0001011) begin //ReLU
            if (funct3 == 3'b000) begin
                if ($signed(rs1_data) < 0)
                    alu_result = 32'd0;
                else
                    alu_result = rs1_data;
            end
        end else begin
            alu_result = 32'd0;
        end
    end


    always_ff @(posedge clk or posedge reset) begin
        if (!reset) begin
            if ((opcode == 7'b0010011) || (opcode == 7'b0110011) || (opcode == 7'b0001011)) begin
                if (rd != 5'd0)
                    regs[rd] <= alu_result;
            end
        end
    end

endmodule

tb_SingleCycleCPU.sv
`timescale 1ns/1ps

module tb_SingleCycleCPU;
    logic clk;
    logic reset;
    logic [31:0] cycle_count;

    // 实例化单周期 CPU 模块
    // 注意：确保 SingleCycleCPU 模块中有公开的 PC 信号（例如 PC）
    SingleCycleCPU dut(
        .clk(clk),
        .reset(reset)
    );

    // 产生时钟：周期50 ns（每25 ns翻转一次）
    always #25 clk = ~clk;

    // 计数器：在每个时钟上升沿累加周期数
    initial begin
        cycle_count = 0;
        forever @(posedge clk) begin
            cycle_count = cycle_count + 1;
        end
    end

    // 仿真流程：复位后等待直到PC达到400（即执行100条指令），然后输出结果并结束仿真
    initial begin
        reset = 1;
        #50;         // 复位50 ns
        reset = 0;
        wait (dut.PC >= 32'd400); // 当 PC 达到400时，认为100条指令已完成
        $display("Single Cycle CPU Simulation Results:");
        $display("  Total cycles = %0d", cycle_count);
        $display("  Final PC     = %0d", dut.PC);
        // 有效指令数 = PC/4；真实 CPI = 总周期数 / (PC/4)
        $display("  Effective CPI = %0f", cycle_count / (dut.PC / 4.0));
        $finish;
    end

    // 波形记录
    initial begin
        $dumpfile("tb_SingleCycleCPU.vcd");
        $dumpvars(0, tb_SingleCycleCPU);
    end
endmodule

tb_SingleCycleCPU.vcd
$date
	Tue Mar 18 05:06:39 2025
$end
$version
	ModelSim Version 2020.1
$end
$timescale
	1ps
$end

$scope module tb_SingleCycleCPU $end
$var reg 1 ! clk $end
$var reg 1 " reset $end
$var reg 32 # cycle_count [31:0] $end

$scope module dut $end
$var wire 1 $ clk $end
$var wire 1 % reset $end
$var reg 32 & PC [31:0] $end
$var reg 32 ' instruction [31:0] $end
$var integer 32 ( i $end
$var wire 1 ) rs1_data [31] $end
$var wire 1 * rs1_data [30] $end
$var wire 1 + rs1_data [29] $end
$var wire 1 , rs1_data [28] $end
$var wire 1 - rs1_data [27] $end
$var wire 1 . rs1_data [26] $end
$var wire 1 / rs1_data [25] $end
$var wire 1 0 rs1_data [24] $end
$var wire 1 1 rs1_data [23] $end
$var wire 1 2 rs1_data [22] $end
$var wire 1 3 rs1_data [21] $end
$var wire 1 4 rs1_data [20] $end
$var wire 1 5 rs1_data [19] $end
$var wire 1 6 rs1_data [18] $end
$var wire 1 7 rs1_data [17] $end
$var wire 1 8 rs1_data [16] $end
$var wire 1 9 rs1_data [15] $end
$var wire 1 : rs1_data [14] $end
$var wire 1 ; rs1_data [13] $end
$var wire 1 < rs1_data [12] $end
$var wire 1 = rs1_data [11] $end
$var wire 1 > rs1_data [10] $end
$var wire 1 ? rs1_data [9] $end
$var wire 1 @ rs1_data [8] $end
$var wire 1 A rs1_data [7] $end
$var wire 1 B rs1_data [6] $end
$var wire 1 C rs1_data [5] $end
$var wire 1 D rs1_data [4] $end
$var wire 1 E rs1_data [3] $end
$var wire 1 F rs1_data [2] $end
$var wire 1 G rs1_data [1] $end
$var wire 1 H rs1_data [0] $end
$var wire 1 I rs2_data [31] $end
$var wire 1 J rs2_data [30] $end
$var wire 1 K rs2_data [29] $end
$var wire 1 L rs2_data [28] $end
$var wire 1 M rs2_data [27] $end
$var wire 1 N rs2_data [26] $end
$var wire 1 O rs2_data [25] $end
$var wire 1 P rs2_data [24] $end
$var wire 1 Q rs2_data [23] $end
$var wire 1 R rs2_data [22] $end
$var wire 1 S rs2_data [21] $end
$var wire 1 T rs2_data [20] $end
$var wire 1 U rs2_data [19] $end
$var wire 1 V rs2_data [18] $end
$var wire 1 W rs2_data [17] $end
$var wire 1 X rs2_data [16] $end
$var wire 1 Y rs2_data [15] $end
$var wire 1 Z rs2_data [14] $end
$var wire 1 [ rs2_data [13] $end
$var wire 1 \ rs2_data [12] $end
$var wire 1 ] rs2_data [11] $end
$var wire 1 ^ rs2_data [10] $end
$var wire 1 _ rs2_data [9] $end
$var wire 1 ` rs2_data [8] $end
$var wire 1 a rs2_data [7] $end
$var wire 1 b rs2_data [6] $end
$var wire 1 c rs2_data [5] $end
$var wire 1 d rs2_data [4] $end
$var wire 1 e rs2_data [3] $end
$var wire 1 f rs2_data [2] $end
$var wire 1 g rs2_data [1] $end
$var wire 1 h rs2_data [0] $end
$var reg 7 i opcode [6:0] $end
$var reg 5 j rd [4:0] $end
$var reg 3 k funct3 [2:0] $end
$var reg 5 l rs1 [4:0] $end
$var reg 5 m rs2 [4:0] $end
$var reg 7 n funct7 [6:0] $end
$var reg 32 o imm [31:0] $end
$var reg 32 p alu_result [31:0] $end
$upscope $end
$upscope $end
$enddefinitions $end
#0
$dumpvars
0!
1"
b0 #
b0 &
b10011 '
b10011 i
b0 j
b0 k
b0 l
b0 m
b0 n
b0 o
b0 p
b100000 (
0H
0G
0F
0E
0D
0C
0B
0A
0@
0?
0>
0=
0<
0;
0:
09
08
07
06
05
04
03
02
01
00
0/
0.
0-
0,
0+
0*
0)
0h
0g
0f
0e
0d
0c
0b
0a
0`
0_
0^
0]
0\
0[
0Z
0Y
0X
0W
0V
0U
0T
0S
0R
0Q
0P
0O
0N
0M
0L
0K
0J
0I
0$
1%
$end
#25000
1!
1$
b0 (
b1 (
b10 (
b11 (
b100 (
b101 (
b110 (
b111 (
b1000 (
b1001 (
b1010 (
b1011 (
b1100 (
b1101 (
b1110 (
b1111 (
b10000 (
b10001 (
b10010 (
b10011 (
b10100 (
b10101 (
b10110 (
b10111 (
b11000 (
b11001 (
b11010 (
b11011 (
b11100 (
b11101 (
b11110 (
b11111 (
b100000 (
b1 #
#50000
0"
0!
0%
0$
#75000
1!
1$
b10 #
b100 &
b11111111010100010000000100010011 '
b10 j
b10 l
b10101 m
b1111111 n
b11111111111111111111111111110101 o
b11111111111111111111111111110101 p
#100000
0!
0$
#125000
1!
1$
b11 #
b1000 &
b1000000100001011 '
b1011 i
b1 l
b0 m
b0 n
b0 o
b0 p
#150000
0!
0$
#175000
1!
1$
b100 #
b1100 &
b10000011001001010001011 '
b101 j
b1 k
b11 l
b100 m
b100 o
#200000
0!
0$
#225000
1!
1$
b101 #
b10000 &
b11100110010010000001011 '
b1000 j
b10 k
b110 l
b111 m
b111 o
#250000
0!
0$
#275000
1!
1$
b110 #
b10100 &
b1001011010100001011 '
b1010 j
b11 k
b1001 l
b0 m
b0 o
#300000
0!
0$
#325000
1!
1$
b111 #
b11000 &
b10011 '
b10011 i
b0 j
b0 k
b0 l
#350000
0!
0$
#375000
1!
1$
b1000 #
b11100 &
#400000
0!
0$
#425000
1!
1$
b1001 #
b100000 &
bx '
xH
xG
xF
xE
xD
xC
xB
xA
x@
x?
x>
x=
x<
x;
x:
x9
x8
x7
x6
x5
x4
x3
x2
x1
x0
x/
x.
x-
x,
x+
x*
x)
xh
xg
xf
xe
xd
xc
xb
xa
x`
x_
x^
x]
x\
x[
xZ
xY
xX
xW
xV
xU
xT
xS
xR
xQ
xP
xO
xN
xM
xL
xK
xJ
xI
bx p
bx i
bx j
bx k
bx l
bx m
bx n
bx o
b0 p
#450000
0!
0$
#475000
1!
1$
b1010 #
b100100 &
#500000
0!
0$
#525000
1!
1$
b1011 #
b101000 &
#550000
0!
0$
#575000
1!
1$
b1100 #
b101100 &
#600000
0!
0$
#625000
1!
1$
b1101 #
b110000 &
#650000
0!
0$
#675000
1!
1$
b1110 #
b110100 &
#700000
0!
0$
#725000
1!
1$
b1111 #
b111000 &
#750000
0!
0$
#775000
1!
1$
b10000 #
b111100 &
#800000
0!
0$
#825000
1!
1$
b10001 #
b1000000 &
#850000
0!
0$
#875000
1!
1$
b10010 #
b1000100 &
#900000
0!
0$
#925000
1!
1$
b10011 #
b1001000 &
#950000
0!
0$
#975000
1!
1$
b10100 #
b1001100 &
#1000000
0!
0$
#1025000
1!
1$
b10101 #
b1010000 &
#1050000
0!
0$
#1075000
1!
1$
b10110 #
b1010100 &
#1100000
0!
0$
#1125000
1!
1$
b10111 #
b1011000 &
#1150000
0!
0$
#1175000
1!
1$
b11000 #
b1011100 &
#1200000
0!
0$
#1225000
1!
1$
b11001 #
b1100000 &
#1250000
0!
0$
#1275000
1!
1$
b11010 #
b1100100 &
#1300000
0!
0$
#1325000
1!
1$
b11011 #
b1101000 &
#1350000
0!
0$
#1375000
1!
1$
b11100 #
b1101100 &
#1400000
0!
0$
#1425000
1!
1$
b11101 #
b1110000 &
#1450000
0!
0$
#1475000
1!
1$
b11110 #
b1110100 &
#1500000
0!
0$
#1525000
1!
1$
b11111 #
b1111000 &
#1550000
0!
0$
#1575000
1!
1$
b100000 #
b1111100 &
#1600000
0!
0$
#1625000
1!
1$
b100001 #
b10000000 &
#1650000
0!
0$
#1675000
1!
1$
b100010 #
b10000100 &
#1700000
0!
0$
#1725000
1!
1$
b100011 #
b10001000 &
#1750000
0!
0$
#1775000
1!
1$
b100100 #
b10001100 &
#1800000
0!
0$
#1825000
1!
1$
b100101 #
b10010000 &
#1850000
0!
0$
#1875000
1!
1$
b100110 #
b10010100 &
#1900000
0!
0$
#1925000
1!
1$
b100111 #
b10011000 &
#1950000
0!
0$
#1975000
1!
1$
b101000 #
b10011100 &
#2000000
0!
0$
#2025000
1!
1$
b101001 #
b10100000 &
#2050000
0!
0$
#2075000
1!
1$
b101010 #
b10100100 &
#2100000
0!
0$
#2125000
1!
1$
b101011 #
b10101000 &
#2150000
0!
0$
#2175000
1!
1$
b101100 #
b10101100 &
#2200000
0!
0$
#2225000
1!
1$
b101101 #
b10110000 &
#2250000
0!
0$
#2275000
1!
1$
b101110 #
b10110100 &
#2300000
0!
0$
#2325000
1!
1$
b101111 #
b10111000 &
#2350000
0!
0$
#2375000
1!
1$
b110000 #
b10111100 &
#2400000
0!
0$
#2425000
1!
1$
b110001 #
b11000000 &
#2450000
0!
0$
#2475000
1!
1$
b110010 #
b11000100 &
#2500000
0!
0$
#2525000
1!
1$
b110011 #
b11001000 &
